{
    "Title": [
        "Манга У меня 90 миллиардов на счету",
        "I have 90 billion licking gold",
        "Wo you jiuqian wanyi tangou jin 我有九千万亿舔狗金",
        "Wǒ yǒu jiǔqiān wànyì tiǎngǒu jīn"
    ],
    "Description": "Описание  манги У меня 90 миллиардов на счету : Чэнь Юань, студент обычного колледжа, получил Шэньхао-систему и немало денег - 90 миллиардов. Однако тратить их можно только на девушек. Чтобы использовать все деньги, Чэнь Юань решил добиться знаменитости!",
    "Genre": [
        "комедия ",
        "фэнтези ",
        "гарем ",
        "сёнэн ",
        "повседневность "
    ],
    "Chapters": [
        {
            "Title": "Том 1 Глава 258",
            "Date": "2 дня назад",
            "Link": "/manga/i-have-90-billion-licking-gold/chapter/1-258",
            "Pages": {
                "ImageURL": ""
            }
        },
        {
            "Title": "Том 1 Глава 256",
            "Date": "3 дня назад",
            "Link": "/manga/i-have-90-billion-licking-gold/chapter/1-256",
            "Pages": {
                "ImageURL": ""
            }
        },
        {
            "Title": "Том 1 Глава 255",
            "Date": "3 дня назад",
            "Link": "/manga/i-have-90-billion-licking-gold/chapter/1-255",
            "Pages": {
                "ImageURL": ""
            }
        },
        {
            "Title": "Том 1 Глава 254",
            "Date": "3 дня назад",
            "Link": "/manga/i-have-90-billion-licking-gold/chapter/1-254",
            "Pages": {
                "ImageURL": ""
            }
        },
        {
            "Title": "Том 1 Глава 253",
            "Date": "3 дня назад",
            "Link": "/manga/i-have-90-billion-licking-gold/chapter/1-253",
            "Pages": {
                "ImageURL": ""
            }
        },
        {
            "Title": "Том 1 Глава 252",
            "Date": "3 дня назад",
            "Link": "/manga/i-have-90-billion-licking-gold/chapter/1-252",
            "Pages": {
                "ImageURL": ""
            }
        },
        {
            "Title": "Том 1 Глава 251",
            "Date": "3 дня назад",
            "Link": "/manga/i-have-90-billion-licking-gold/chapter/1-251",
            "Pages": {
                "ImageURL": ""
            }
        },
        {
            "Title": "Том 1 Глава 250",
            "Date": "18 июня 2024",
            "Link": "/manga/i-have-90-billion-licking-gold/chapter/1-250",
            "Pages": {
                "ImageURL": ""
            }
        },
        {
            "Title": "Том 1 Глава 247",
            "Date": "13 июня 2024",
            "Link": "/manga/i-have-90-billion-licking-gold/chapter/1-247",
            "Pages": {
                "ImageURL": ""
            }
        },
        {
            "Title": "Том 1 Глава 246",
            "Date": "13 июня 2024",
            "Link": "/manga/i-have-90-billion-licking-gold/chapter/1-246",
            "Pages": {
                "ImageURL": ""
            }
        },
        {
            "Title": "Том 1 Глава 245",
            "Date": "13 июня 2024",
            "Link": "/manga/i-have-90-billion-licking-gold/chapter/1-245",
            "Pages": {
                "ImageURL": ""
            }
        },
        {
            "Title": "Том 1 Глава 244",
            "Date": "10 июня 2024",
            "Link": "/manga/i-have-90-billion-licking-gold/chapter/1-244",
            "Pages": {
                "ImageURL": ""
            }
        },
        {
            "Title": "Том 1 Глава 243",
            "Date": "9 июня 2024",
            "Link": "/manga/i-have-90-billion-licking-gold/chapter/1-243",
            "Pages": {
                "ImageURL": ""
            }
        },
        {
            "Title": "Том 1 Глава 242",
            "Date": "8 июня 2024",
            "Link": "/manga/i-have-90-billion-licking-gold/chapter/1-242",
            "Pages": {
                "ImageURL": ""
            }
        },
        {
            "Title": "Том 1 Глава 239",
            "Date": "5 июня 2024",
            "Link": "/manga/i-have-90-billion-licking-gold/chapter/1-239",
            "Pages": {
                "ImageURL": ""
            }
        },
        {
            "Title": "Том 1 Глава 236",
            "Date": "3 июня 2024",
            "Link": "/manga/i-have-90-billion-licking-gold/chapter/1-236",
            "Pages": {
                "ImageURL": ""
            }
        },
        {
            "Title": "Том 1 Глава 234",
            "Date": "31 мая 2024",
            "Link": "/manga/i-have-90-billion-licking-gold/chapter/1-234",
            "Pages": {
                "ImageURL": ""
            }
        },
        {
            "Title": "Том 1 Глава 233",
            "Date": "31 мая 2024",
            "Link": "/manga/i-have-90-billion-licking-gold/chapter/1-233",
            "Pages": {
                "ImageURL": ""
            }
        },
        {
            "Title": "Том 1 Глава 232",
            "Date": "31 мая 2024",
            "Link": "/manga/i-have-90-billion-licking-gold/chapter/1-232",
            "Pages": {
                "ImageURL": ""
            }
        },
        {
            "Title": "Том 1 Глава 231",
            "Date": "31 мая 2024",
            "Link": "/manga/i-have-90-billion-licking-gold/chapter/1-231",
            "Pages": {
                "ImageURL": ""
            }
        },
        {
            "Title": "Том 1 Глава 230",
            "Date": "31 мая 2024",
            "Link": "/manga/i-have-90-billion-licking-gold/chapter/1-230",
            "Pages": {
                "ImageURL": ""
            }
        },
        {
            "Title": "Том 1 Глава 229",
            "Date": "31 мая 2024",
            "Link": "/manga/i-have-90-billion-licking-gold/chapter/1-229",
            "Pages": {
                "ImageURL": ""
            }
        },
        {
            "Title": "Том 1 Глава 228",
            "Date": "31 мая 2024",
            "Link": "/manga/i-have-90-billion-licking-gold/chapter/1-228",
            "Pages": {
                "ImageURL": ""
            }
        },
        {
            "Title": "Том 1 Глава 227",
            "Date": "31 мая 2024",
            "Link": "/manga/i-have-90-billion-licking-gold/chapter/1-227",
            "Pages": {
                "ImageURL": ""
            }
        },
        {
            "Title": "Том 1 Глава 226",
            "Date": "31 мая 2024",
            "Link": "/manga/i-have-90-billion-licking-gold/chapter/1-226",
            "Pages": {
                "ImageURL": ""
            }
        },
        {
            "Title": "Том 1 Глава 225",
            "Date": "31 мая 2024",
            "Link": "/manga/i-have-90-billion-licking-gold/chapter/1-225",
            "Pages": {
                "ImageURL": ""
            }
        },
        {
            "Title": "Том 1 Глава 224",
            "Date": "31 мая 2024",
            "Link": "/manga/i-have-90-billion-licking-gold/chapter/1-224",
            "Pages": {
                "ImageURL": ""
            }
        },
        {
            "Title": "Том 1 Глава 223",
            "Date": "31 мая 2024",
            "Link": "/manga/i-have-90-billion-licking-gold/chapter/1-223",
            "Pages": {
                "ImageURL": ""
            }
        },
        {
            "Title": "Том 1 Глава 222",
            "Date": "31 мая 2024",
            "Link": "/manga/i-have-90-billion-licking-gold/chapter/1-222",
            "Pages": {
                "ImageURL": ""
            }
        },
        {
            "Title": "Том 1 Глава 221",
            "Date": "31 мая 2024",
            "Link": "/manga/i-have-90-billion-licking-gold/chapter/1-221",
            "Pages": {
                "ImageURL": ""
            }
        },
        {
            "Title": "Том 1 Глава 220",
            "Date": "31 мая 2024",
            "Link": "/manga/i-have-90-billion-licking-gold/chapter/1-220",
            "Pages": {
                "ImageURL": ""
            }
        },
        {
            "Title": "Том 1 Глава 219",
            "Date": "31 мая 2024",
            "Link": "/manga/i-have-90-billion-licking-gold/chapter/1-219",
            "Pages": {
                "ImageURL": ""
            }
        },
        {
            "Title": "Том 1 Глава 218",
            "Date": "31 мая 2024",
            "Link": "/manga/i-have-90-billion-licking-gold/chapter/1-218",
            "Pages": {
                "ImageURL": ""
            }
        },
        {
            "Title": "Том 1 Глава 217",
            "Date": "31 мая 2024",
            "Link": "/manga/i-have-90-billion-licking-gold/chapter/1-217",
            "Pages": {
                "ImageURL": ""
            }
        },
        {
            "Title": "Том 1 Глава 216",
            "Date": "31 мая 2024",
            "Link": "/manga/i-have-90-billion-licking-gold/chapter/1-216",
            "Pages": {
                "ImageURL": ""
            }
        },
        {
            "Title": "Том 1 Глава 215",
            "Date": "31 мая 2024",
            "Link": "/manga/i-have-90-billion-licking-gold/chapter/1-215",
            "Pages": {
                "ImageURL": ""
            }
        },
        {
            "Title": "Том 1 Глава 214",
            "Date": "31 мая 2024",
            "Link": "/manga/i-have-90-billion-licking-gold/chapter/1-214",
            "Pages": {
                "ImageURL": ""
            }
        },
        {
            "Title": "Том 1 Глава 213",
            "Date": "31 мая 2024",
            "Link": "/manga/i-have-90-billion-licking-gold/chapter/1-213",
            "Pages": {
                "ImageURL": ""
            }
        },
        {
            "Title": "Том 1 Глава 212",
            "Date": "31 мая 2024",
            "Link": "/manga/i-have-90-billion-licking-gold/chapter/1-212",
            "Pages": {
                "ImageURL": ""
            }
        },
        {
            "Title": "Том 1 Глава 211",
            "Date": "8 мая 2024",
            "Link": "/manga/i-have-90-billion-licking-gold/chapter/1-211",
            "Pages": {
                "ImageURL": ""
            }
        },
        {
            "Title": "Том 1 Глава 210",
            "Date": "8 мая 2024",
            "Link": "/manga/i-have-90-billion-licking-gold/chapter/1-210",
            "Pages": {
                "ImageURL": ""
            }
        },
        {
            "Title": "Том 1 Глава 209",
            "Date": "8 мая 2024",
            "Link": "/manga/i-have-90-billion-licking-gold/chapter/1-209",
            "Pages": {
                "ImageURL": ""
            }
        },
        {
            "Title": "Том 1 Глава 208",
            "Date": "8 мая 2024",
            "Link": "/manga/i-have-90-billion-licking-gold/chapter/1-208",
            "Pages": {
                "ImageURL": ""
            }
        },
        {
            "Title": "Том 1 Глава 207",
            "Date": "8 мая 2024",
            "Link": "/manga/i-have-90-billion-licking-gold/chapter/1-207",
            "Pages": {
                "ImageURL": ""
            }
        },
        {
            "Title": "Том 1 Глава 206",
            "Date": "8 мая 2024",
            "Link": "/manga/i-have-90-billion-licking-gold/chapter/1-206",
            "Pages": {
                "ImageURL": ""
            }
        },
        {
            "Title": "Том 1 Глава 205",
            "Date": "8 мая 2024",
            "Link": "/manga/i-have-90-billion-licking-gold/chapter/1-205",
            "Pages": {
                "ImageURL": ""
            }
        },
        {
            "Title": "Том 1 Глава 204",
            "Date": "8 мая 2024",
            "Link": "/manga/i-have-90-billion-licking-gold/chapter/1-204",
            "Pages": {
                "ImageURL": ""
            }
        },
        {
            "Title": "Том 1 Глава 203",
            "Date": "8 мая 2024",
            "Link": "/manga/i-have-90-billion-licking-gold/chapter/1-203",
            "Pages": {
                "ImageURL": ""
            }
        },
        {
            "Title": "Том 1 Глава 202",
            "Date": "8 мая 2024",
            "Link": "/manga/i-have-90-billion-licking-gold/chapter/1-202",
            "Pages": {
                "ImageURL": ""
            }
        },
        {
            "Title": "Том 1 Глава 201",
            "Date": "8 мая 2024",
            "Link": "/manga/i-have-90-billion-licking-gold/chapter/1-201",
            "Pages": {
                "ImageURL": ""
            }
        },
        {
            "Title": "Том 1 Глава 200",
            "Date": "8 мая 2024",
            "Link": "/manga/i-have-90-billion-licking-gold/chapter/1-200",
            "Pages": {
                "ImageURL": ""
            }
        },
        {
            "Title": "Том 1 Глава 199",
            "Date": "26 апреля 2024",
            "Link": "/manga/i-have-90-billion-licking-gold/chapter/1-199",
            "Pages": {
                "ImageURL": ""
            }
        },
        {
            "Title": "Том 1 Глава 198",
            "Date": "26 апреля 2024",
            "Link": "/manga/i-have-90-billion-licking-gold/chapter/1-198",
            "Pages": {
                "ImageURL": ""
            }
        },
        {
            "Title": "Том 1 Глава 197",
            "Date": "26 апреля 2024",
            "Link": "/manga/i-have-90-billion-licking-gold/chapter/1-197",
            "Pages": {
                "ImageURL": ""
            }
        },
        {
            "Title": "Том 1 Глава 196",
            "Date": "26 апреля 2024",
            "Link": "/manga/i-have-90-billion-licking-gold/chapter/1-196",
            "Pages": {
                "ImageURL": ""
            }
        },
        {
            "Title": "Том 1 Глава 195",
            "Date": "26 апреля 2024",
            "Link": "/manga/i-have-90-billion-licking-gold/chapter/1-195",
            "Pages": {
                "ImageURL": ""
            }
        },
        {
            "Title": "Том 1 Глава 194",
            "Date": "26 апреля 2024",
            "Link": "/manga/i-have-90-billion-licking-gold/chapter/1-194",
            "Pages": {
                "ImageURL": ""
            }
        },
        {
            "Title": "Том 1 Глава 193",
            "Date": "26 апреля 2024",
            "Link": "/manga/i-have-90-billion-licking-gold/chapter/1-193",
            "Pages": {
                "ImageURL": ""
            }
        },
        {
            "Title": "Том 1 Глава 192",
            "Date": "26 апреля 2024",
            "Link": "/manga/i-have-90-billion-licking-gold/chapter/1-192",
            "Pages": {
                "ImageURL": ""
            }
        },
        {
            "Title": "Том 1 Глава 191",
            "Date": "26 апреля 2024",
            "Link": "/manga/i-have-90-billion-licking-gold/chapter/1-191",
            "Pages": {
                "ImageURL": ""
            }
        },
        {
            "Title": "Том 1 Глава 190",
            "Date": "26 апреля 2024",
            "Link": "/manga/i-have-90-billion-licking-gold/chapter/1-190",
            "Pages": {
                "ImageURL": ""
            }
        },
        {
            "Title": "Том 1 Глава 189",
            "Date": "16 апреля 2024",
            "Link": "/manga/i-have-90-billion-licking-gold/chapter/1-189",
            "Pages": {
                "ImageURL": ""
            }
        },
        {
            "Title": "Том 1 Глава 188",
            "Date": "16 апреля 2024",
            "Link": "/manga/i-have-90-billion-licking-gold/chapter/1-188",
            "Pages": {
                "ImageURL": ""
            }
        },
        {
            "Title": "Том 1 Глава 187",
            "Date": "16 апреля 2024",
            "Link": "/manga/i-have-90-billion-licking-gold/chapter/1-187",
            "Pages": {
                "ImageURL": ""
            }
        },
        {
            "Title": "Том 1 Глава 186",
            "Date": "16 апреля 2024",
            "Link": "/manga/i-have-90-billion-licking-gold/chapter/1-186",
            "Pages": {
                "ImageURL": ""
            }
        },
        {
            "Title": "Том 1 Глава 185",
            "Date": "16 апреля 2024",
            "Link": "/manga/i-have-90-billion-licking-gold/chapter/1-185",
            "Pages": {
                "ImageURL": ""
            }
        },
        {
            "Title": "Том 1 Глава 184",
            "Date": "16 апреля 2024",
            "Link": "/manga/i-have-90-billion-licking-gold/chapter/1-184",
            "Pages": {
                "ImageURL": ""
            }
        },
        {
            "Title": "Том 1 Глава 183",
            "Date": "16 апреля 2024",
            "Link": "/manga/i-have-90-billion-licking-gold/chapter/1-183",
            "Pages": {
                "ImageURL": ""
            }
        },
        {
            "Title": "Том 1 Глава 182",
            "Date": "16 апреля 2024",
            "Link": "/manga/i-have-90-billion-licking-gold/chapter/1-182",
            "Pages": {
                "ImageURL": ""
            }
        },
        {
            "Title": "Том 1 Глава 181",
            "Date": "16 апреля 2024",
            "Link": "/manga/i-have-90-billion-licking-gold/chapter/1-181",
            "Pages": {
                "ImageURL": ""
            }
        },
        {
            "Title": "Том 1 Глава 180",
            "Date": "8 апреля 2024",
            "Link": "/manga/i-have-90-billion-licking-gold/chapter/1-180",
            "Pages": {
                "ImageURL": ""
            }
        },
        {
            "Title": "Том 1 Глава 179",
            "Date": "8 апреля 2024",
            "Link": "/manga/i-have-90-billion-licking-gold/chapter/1-179",
            "Pages": {
                "ImageURL": ""
            }
        },
        {
            "Title": "Том 1 Глава 178",
            "Date": "8 апреля 2024",
            "Link": "/manga/i-have-90-billion-licking-gold/chapter/1-178",
            "Pages": {
                "ImageURL": ""
            }
        },
        {
            "Title": "Том 1 Глава 177",
            "Date": "8 апреля 2024",
            "Link": "/manga/i-have-90-billion-licking-gold/chapter/1-177",
            "Pages": {
                "ImageURL": ""
            }
        },
        {
            "Title": "Том 1 Глава 176",
            "Date": "8 апреля 2024",
            "Link": "/manga/i-have-90-billion-licking-gold/chapter/1-176",
            "Pages": {
                "ImageURL": ""
            }
        },
        {
            "Title": "Том 1 Глава 175",
            "Date": "8 апреля 2024",
            "Link": "/manga/i-have-90-billion-licking-gold/chapter/1-175",
            "Pages": {
                "ImageURL": ""
            }
        },
        {
            "Title": "Том 1 Глава 174",
            "Date": "8 апреля 2024",
            "Link": "/manga/i-have-90-billion-licking-gold/chapter/1-174",
            "Pages": {
                "ImageURL": ""
            }
        },
        {
            "Title": "Том 1 Глава 173",
            "Date": "8 апреля 2024",
            "Link": "/manga/i-have-90-billion-licking-gold/chapter/1-173",
            "Pages": {
                "ImageURL": ""
            }
        },
        {
            "Title": "Том 1 Глава 172",
            "Date": "8 апреля 2024",
            "Link": "/manga/i-have-90-billion-licking-gold/chapter/1-172",
            "Pages": {
                "ImageURL": ""
            }
        },
        {
            "Title": "Том 1 Глава 171",
            "Date": "8 апреля 2024",
            "Link": "/manga/i-have-90-billion-licking-gold/chapter/1-171",
            "Pages": {
                "ImageURL": ""
            }
        },
        {
            "Title": "Том 1 Глава 170",
            "Date": "8 апреля 2024",
            "Link": "/manga/i-have-90-billion-licking-gold/chapter/1-170",
            "Pages": {
                "ImageURL": ""
            }
        },
        {
            "Title": "Том 1 Глава 169",
            "Date": "8 апреля 2024",
            "Link": "/manga/i-have-90-billion-licking-gold/chapter/1-169",
            "Pages": {
                "ImageURL": ""
            }
        },
        {
            "Title": "Том 1 Глава 168",
            "Date": "8 апреля 2024",
            "Link": "/manga/i-have-90-billion-licking-gold/chapter/1-168",
            "Pages": {
                "ImageURL": ""
            }
        },
        {
            "Title": "Том 1 Глава 167",
            "Date": "27 марта 2024",
            "Link": "/manga/i-have-90-billion-licking-gold/chapter/1-167",
            "Pages": {
                "ImageURL": ""
            }
        },
        {
            "Title": "Том 1 Глава 166",
            "Date": "27 марта 2024",
            "Link": "/manga/i-have-90-billion-licking-gold/chapter/1-166",
            "Pages": {
                "ImageURL": ""
            }
        },
        {
            "Title": "Том 1 Глава 165",
            "Date": "27 марта 2024",
            "Link": "/manga/i-have-90-billion-licking-gold/chapter/1-165",
            "Pages": {
                "ImageURL": ""
            }
        },
        {
            "Title": "Том 1 Глава 164",
            "Date": "27 марта 2024",
            "Link": "/manga/i-have-90-billion-licking-gold/chapter/1-164",
            "Pages": {
                "ImageURL": ""
            }
        },
        {
            "Title": "Том 1 Глава 163",
            "Date": "27 марта 2024",
            "Link": "/manga/i-have-90-billion-licking-gold/chapter/1-163",
            "Pages": {
                "ImageURL": ""
            }
        },
        {
            "Title": "Том 1 Глава 162",
            "Date": "27 марта 2024",
            "Link": "/manga/i-have-90-billion-licking-gold/chapter/1-162",
            "Pages": {
                "ImageURL": ""
            }
        },
        {
            "Title": "Том 1 Глава 161",
            "Date": "27 марта 2024",
            "Link": "/manga/i-have-90-billion-licking-gold/chapter/1-161",
            "Pages": {
                "ImageURL": ""
            }
        },
        {
            "Title": "Том 1 Глава 160",
            "Date": "22 марта 2024",
            "Link": "/manga/i-have-90-billion-licking-gold/chapter/1-160",
            "Pages": {
                "ImageURL": ""
            }
        },
        {
            "Title": "Том 1 Глава 159",
            "Date": "22 марта 2024",
            "Link": "/manga/i-have-90-billion-licking-gold/chapter/1-159",
            "Pages": {
                "ImageURL": ""
            }
        },
        {
            "Title": "Том 1 Глава 158",
            "Date": "21 марта 2024",
            "Link": "/manga/i-have-90-billion-licking-gold/chapter/1-158",
            "Pages": {
                "ImageURL": ""
            }
        },
        {
            "Title": "Том 1 Глава 157",
            "Date": "20 марта 2024",
            "Link": "/manga/i-have-90-billion-licking-gold/chapter/1-157",
            "Pages": {
                "ImageURL": ""
            }
        },
        {
            "Title": "Том 1 Глава 156",
            "Date": "19 марта 2024",
            "Link": "/manga/i-have-90-billion-licking-gold/chapter/1-156",
            "Pages": {
                "ImageURL": ""
            }
        },
        {
            "Title": "Том 1 Глава 155",
            "Date": "18 марта 2024",
            "Link": "/manga/i-have-90-billion-licking-gold/chapter/1-155",
            "Pages": {
                "ImageURL": ""
            }
        },
        {
            "Title": "Том 1 Глава 154",
            "Date": "17 марта 2024",
            "Link": "/manga/i-have-90-billion-licking-gold/chapter/1-154",
            "Pages": {
                "ImageURL": ""
            }
        },
        {
            "Title": "Том 1 Глава 153",
            "Date": "16 марта 2024",
            "Link": "/manga/i-have-90-billion-licking-gold/chapter/1-153",
            "Pages": {
                "ImageURL": ""
            }
        },
        {
            "Title": "Том 1 Глава 152",
            "Date": "15 марта 2024",
            "Link": "/manga/i-have-90-billion-licking-gold/chapter/1-152",
            "Pages": {
                "ImageURL": ""
            }
        },
        {
            "Title": "Том 1 Глава 151",
            "Date": "14 марта 2024",
            "Link": "/manga/i-have-90-billion-licking-gold/chapter/1-151",
            "Pages": {
                "ImageURL": ""
            }
        },
        {
            "Title": "Том 1 Глава 150",
            "Date": "14 марта 2024",
            "Link": "/manga/i-have-90-billion-licking-gold/chapter/1-150",
            "Pages": {
                "ImageURL": ""
            }
        },
        {
            "Title": "Том 1 Глава 149",
            "Date": "13 марта 2024",
            "Link": "/manga/i-have-90-billion-licking-gold/chapter/1-149",
            "Pages": {
                "ImageURL": ""
            }
        },
        {
            "Title": "Том 1 Глава 148",
            "Date": "13 марта 2024",
            "Link": "/manga/i-have-90-billion-licking-gold/chapter/1-148",
            "Pages": {
                "ImageURL": ""
            }
        },
        {
            "Title": "Том 1 Глава 147",
            "Date": "13 марта 2024",
            "Link": "/manga/i-have-90-billion-licking-gold/chapter/1-147",
            "Pages": {
                "ImageURL": ""
            }
        },
        {
            "Title": "Том 1 Глава 146",
            "Date": "10 марта 2024",
            "Link": "/manga/i-have-90-billion-licking-gold/chapter/1-146",
            "Pages": {
                "ImageURL": ""
            }
        },
        {
            "Title": "Том 1 Глава 145",
            "Date": "9 марта 2024",
            "Link": "/manga/i-have-90-billion-licking-gold/chapter/1-145",
            "Pages": {
                "ImageURL": ""
            }
        },
        {
            "Title": "Том 1 Глава 144",
            "Date": "8 марта 2024",
            "Link": "/manga/i-have-90-billion-licking-gold/chapter/1-144",
            "Pages": {
                "ImageURL": ""
            }
        },
        {
            "Title": "Том 1 Глава 143",
            "Date": "7 марта 2024",
            "Link": "/manga/i-have-90-billion-licking-gold/chapter/1-143",
            "Pages": {
                "ImageURL": ""
            }
        },
        {
            "Title": "Том 1 Глава 142",
            "Date": "7 марта 2024",
            "Link": "/manga/i-have-90-billion-licking-gold/chapter/1-142",
            "Pages": {
                "ImageURL": ""
            }
        },
        {
            "Title": "Том 1 Глава 141",
            "Date": "6 марта 2024",
            "Link": "/manga/i-have-90-billion-licking-gold/chapter/1-141",
            "Pages": {
                "ImageURL": ""
            }
        },
        {
            "Title": "Том 1 Глава 140",
            "Date": "6 марта 2024",
            "Link": "/manga/i-have-90-billion-licking-gold/chapter/1-140",
            "Pages": {
                "ImageURL": ""
            }
        },
        {
            "Title": "Том 1 Глава 139",
            "Date": "6 марта 2024",
            "Link": "/manga/i-have-90-billion-licking-gold/chapter/1-139",
            "Pages": {
                "ImageURL": ""
            }
        },
        {
            "Title": "Том 1 Глава 138",
            "Date": "6 марта 2024",
            "Link": "/manga/i-have-90-billion-licking-gold/chapter/1-138",
            "Pages": {
                "ImageURL": ""
            }
        },
        {
            "Title": "Том 1 Глава 137",
            "Date": "6 марта 2024",
            "Link": "/manga/i-have-90-billion-licking-gold/chapter/1-137",
            "Pages": {
                "ImageURL": ""
            }
        },
        {
            "Title": "Том 1 Глава 136",
            "Date": "6 марта 2024",
            "Link": "/manga/i-have-90-billion-licking-gold/chapter/1-136",
            "Pages": {
                "ImageURL": ""
            }
        },
        {
            "Title": "Том 1 Глава 135",
            "Date": "6 марта 2024",
            "Link": "/manga/i-have-90-billion-licking-gold/chapter/1-135",
            "Pages": {
                "ImageURL": ""
            }
        },
        {
            "Title": "Том 1 Глава 134",
            "Date": "6 марта 2024",
            "Link": "/manga/i-have-90-billion-licking-gold/chapter/1-134",
            "Pages": {
                "ImageURL": ""
            }
        },
        {
            "Title": "Том 1 Глава 133",
            "Date": "6 марта 2024",
            "Link": "/manga/i-have-90-billion-licking-gold/chapter/1-133",
            "Pages": {
                "ImageURL": ""
            }
        },
        {
            "Title": "Том 1 Глава 132",
            "Date": "6 марта 2024",
            "Link": "/manga/i-have-90-billion-licking-gold/chapter/1-132",
            "Pages": {
                "ImageURL": ""
            }
        },
        {
            "Title": "Том 1 Глава 131",
            "Date": "6 марта 2024",
            "Link": "/manga/i-have-90-billion-licking-gold/chapter/1-131",
            "Pages": {
                "ImageURL": ""
            }
        },
        {
            "Title": "Том 1 Глава 130",
            "Date": "6 марта 2024",
            "Link": "/manga/i-have-90-billion-licking-gold/chapter/1-130",
            "Pages": {
                "ImageURL": ""
            }
        },
        {
            "Title": "Том 1 Глава 129",
            "Date": "6 марта 2024",
            "Link": "/manga/i-have-90-billion-licking-gold/chapter/1-129",
            "Pages": {
                "ImageURL": ""
            }
        },
        {
            "Title": "Том 1 Глава 128",
            "Date": "6 марта 2024",
            "Link": "/manga/i-have-90-billion-licking-gold/chapter/1-128",
            "Pages": {
                "ImageURL": ""
            }
        },
        {
            "Title": "Том 1 Глава 127",
            "Date": "6 марта 2024",
            "Link": "/manga/i-have-90-billion-licking-gold/chapter/1-127",
            "Pages": {
                "ImageURL": ""
            }
        },
        {
            "Title": "Том 1 Глава 126",
            "Date": "6 марта 2024",
            "Link": "/manga/i-have-90-billion-licking-gold/chapter/1-126",
            "Pages": {
                "ImageURL": ""
            }
        },
        {
            "Title": "Том 1 Глава 125",
            "Date": "6 марта 2024",
            "Link": "/manga/i-have-90-billion-licking-gold/chapter/1-125",
            "Pages": {
                "ImageURL": ""
            }
        },
        {
            "Title": "Том 1 Глава 124",
            "Date": "6 марта 2024",
            "Link": "/manga/i-have-90-billion-licking-gold/chapter/1-124",
            "Pages": {
                "ImageURL": ""
            }
        },
        {
            "Title": "Том 1 Глава 123",
            "Date": "6 марта 2024",
            "Link": "/manga/i-have-90-billion-licking-gold/chapter/1-123",
            "Pages": {
                "ImageURL": ""
            }
        },
        {
            "Title": "Том 1 Глава 122",
            "Date": "6 марта 2024",
            "Link": "/manga/i-have-90-billion-licking-gold/chapter/1-122",
            "Pages": {
                "ImageURL": ""
            }
        },
        {
            "Title": "Том 1 Глава 121",
            "Date": "6 марта 2024",
            "Link": "/manga/i-have-90-billion-licking-gold/chapter/1-121",
            "Pages": {
                "ImageURL": ""
            }
        },
        {
            "Title": "Том 1 Глава 120",
            "Date": "6 марта 2024",
            "Link": "/manga/i-have-90-billion-licking-gold/chapter/1-120",
            "Pages": {
                "ImageURL": ""
            }
        },
        {
            "Title": "Том 1 Глава 119",
            "Date": "13 февраля 2024",
            "Link": "/manga/i-have-90-billion-licking-gold/chapter/1-119",
            "Pages": {
                "ImageURL": ""
            }
        },
        {
            "Title": "Том 1 Глава 118",
            "Date": "13 февраля 2024",
            "Link": "/manga/i-have-90-billion-licking-gold/chapter/1-118",
            "Pages": {
                "ImageURL": ""
            }
        },
        {
            "Title": "Том 1 Глава 117",
            "Date": "13 февраля 2024",
            "Link": "/manga/i-have-90-billion-licking-gold/chapter/1-117",
            "Pages": {
                "ImageURL": ""
            }
        },
        {
            "Title": "Том 1 Глава 116",
            "Date": "13 февраля 2024",
            "Link": "/manga/i-have-90-billion-licking-gold/chapter/1-116",
            "Pages": {
                "ImageURL": ""
            }
        },
        {
            "Title": "Том 1 Глава 115",
            "Date": "13 февраля 2024",
            "Link": "/manga/i-have-90-billion-licking-gold/chapter/1-115",
            "Pages": {
                "ImageURL": ""
            }
        },
        {
            "Title": "Том 1 Глава 114",
            "Date": "13 февраля 2024",
            "Link": "/manga/i-have-90-billion-licking-gold/chapter/1-114",
            "Pages": {
                "ImageURL": ""
            }
        },
        {
            "Title": "Том 1 Глава 113",
            "Date": "13 февраля 2024",
            "Link": "/manga/i-have-90-billion-licking-gold/chapter/1-113",
            "Pages": {
                "ImageURL": ""
            }
        },
        {
            "Title": "Том 1 Глава 112",
            "Date": "13 февраля 2024",
            "Link": "/manga/i-have-90-billion-licking-gold/chapter/1-112",
            "Pages": {
                "ImageURL": ""
            }
        },
        {
            "Title": "Том 1 Глава 111",
            "Date": "13 февраля 2024",
            "Link": "/manga/i-have-90-billion-licking-gold/chapter/1-111",
            "Pages": {
                "ImageURL": ""
            }
        },
        {
            "Title": "Том 1 Глава 110",
            "Date": "13 февраля 2024",
            "Link": "/manga/i-have-90-billion-licking-gold/chapter/1-110",
            "Pages": {
                "ImageURL": ""
            }
        },
        {
            "Title": "Том 1 Глава 109",
            "Date": "13 февраля 2024",
            "Link": "/manga/i-have-90-billion-licking-gold/chapter/1-109",
            "Pages": {
                "ImageURL": ""
            }
        },
        {
            "Title": "Том 1 Глава 108",
            "Date": "13 февраля 2024",
            "Link": "/manga/i-have-90-billion-licking-gold/chapter/1-108",
            "Pages": {
                "ImageURL": ""
            }
        },
        {
            "Title": "Том 1 Глава 107",
            "Date": "13 февраля 2024",
            "Link": "/manga/i-have-90-billion-licking-gold/chapter/1-107",
            "Pages": {
                "ImageURL": ""
            }
        },
        {
            "Title": "Том 1 Глава 106",
            "Date": "13 февраля 2024",
            "Link": "/manga/i-have-90-billion-licking-gold/chapter/1-106",
            "Pages": {
                "ImageURL": ""
            }
        },
        {
            "Title": "Том 1 Глава 105",
            "Date": "13 февраля 2024",
            "Link": "/manga/i-have-90-billion-licking-gold/chapter/1-105",
            "Pages": {
                "ImageURL": ""
            }
        },
        {
            "Title": "Том 1 Глава 104",
            "Date": "13 февраля 2024",
            "Link": "/manga/i-have-90-billion-licking-gold/chapter/1-104",
            "Pages": {
                "ImageURL": ""
            }
        },
        {
            "Title": "Том 1 Глава 103",
            "Date": "13 февраля 2024",
            "Link": "/manga/i-have-90-billion-licking-gold/chapter/1-103",
            "Pages": {
                "ImageURL": ""
            }
        },
        {
            "Title": "Том 1 Глава 102",
            "Date": "31 января 2024",
            "Link": "/manga/i-have-90-billion-licking-gold/chapter/1-102",
            "Pages": {
                "ImageURL": ""
            }
        },
        {
            "Title": "Том 1 Глава 101",
            "Date": "31 января 2024",
            "Link": "/manga/i-have-90-billion-licking-gold/chapter/1-101",
            "Pages": {
                "ImageURL": ""
            }
        },
        {
            "Title": "Том 1 Глава 100",
            "Date": "31 января 2024",
            "Link": "/manga/i-have-90-billion-licking-gold/chapter/1-100",
            "Pages": {
                "ImageURL": ""
            }
        },
        {
            "Title": "Том 1 Глава 99",
            "Date": "31 января 2024",
            "Link": "/manga/i-have-90-billion-licking-gold/chapter/1-99",
            "Pages": {
                "ImageURL": ""
            }
        },
        {
            "Title": "Том 1 Глава 98",
            "Date": "31 января 2024",
            "Link": "/manga/i-have-90-billion-licking-gold/chapter/1-98",
            "Pages": {
                "ImageURL": ""
            }
        },
        {
            "Title": "Том 1 Глава 97",
            "Date": "31 января 2024",
            "Link": "/manga/i-have-90-billion-licking-gold/chapter/1-97",
            "Pages": {
                "ImageURL": ""
            }
        },
        {
            "Title": "Том 1 Глава 96",
            "Date": "31 января 2024",
            "Link": "/manga/i-have-90-billion-licking-gold/chapter/1-96",
            "Pages": {
                "ImageURL": ""
            }
        },
        {
            "Title": "Том 1 Глава 95",
            "Date": "31 января 2024",
            "Link": "/manga/i-have-90-billion-licking-gold/chapter/1-95",
            "Pages": {
                "ImageURL": ""
            }
        },
        {
            "Title": "Том 1 Глава 94",
            "Date": "31 января 2024",
            "Link": "/manga/i-have-90-billion-licking-gold/chapter/1-94",
            "Pages": {
                "ImageURL": ""
            }
        },
        {
            "Title": "Том 1 Глава 93",
            "Date": "31 января 2024",
            "Link": "/manga/i-have-90-billion-licking-gold/chapter/1-93",
            "Pages": {
                "ImageURL": ""
            }
        },
        {
            "Title": "Том 1 Глава 92",
            "Date": "31 января 2024",
            "Link": "/manga/i-have-90-billion-licking-gold/chapter/1-92",
            "Pages": {
                "ImageURL": ""
            }
        },
        {
            "Title": "Том 1 Глава 91",
            "Date": "31 января 2024",
            "Link": "/manga/i-have-90-billion-licking-gold/chapter/1-91",
            "Pages": {
                "ImageURL": ""
            }
        },
        {
            "Title": "Том 1 Глава 90",
            "Date": "19 января 2024",
            "Link": "/manga/i-have-90-billion-licking-gold/chapter/1-90",
            "Pages": {
                "ImageURL": ""
            }
        },
        {
            "Title": "Том 1 Глава 89",
            "Date": "19 января 2024",
            "Link": "/manga/i-have-90-billion-licking-gold/chapter/1-89",
            "Pages": {
                "ImageURL": ""
            }
        },
        {
            "Title": "Том 1 Глава 88",
            "Date": "19 января 2024",
            "Link": "/manga/i-have-90-billion-licking-gold/chapter/1-88",
            "Pages": {
                "ImageURL": ""
            }
        },
        {
            "Title": "Том 1 Глава 87",
            "Date": "16 января 2024",
            "Link": "/manga/i-have-90-billion-licking-gold/chapter/1-87",
            "Pages": {
                "ImageURL": ""
            }
        },
        {
            "Title": "Том 1 Глава 86",
            "Date": "16 января 2024",
            "Link": "/manga/i-have-90-billion-licking-gold/chapter/1-86",
            "Pages": {
                "ImageURL": ""
            }
        },
        {
            "Title": "Том 1 Глава 85",
            "Date": "16 января 2024",
            "Link": "/manga/i-have-90-billion-licking-gold/chapter/1-85",
            "Pages": {
                "ImageURL": ""
            }
        },
        {
            "Title": "Том 1 Глава 84",
            "Date": "16 января 2024",
            "Link": "/manga/i-have-90-billion-licking-gold/chapter/1-84",
            "Pages": {
                "ImageURL": ""
            }
        },
        {
            "Title": "Том 1 Глава 83",
            "Date": "16 января 2024",
            "Link": "/manga/i-have-90-billion-licking-gold/chapter/1-83",
            "Pages": {
                "ImageURL": ""
            }
        },
        {
            "Title": "Том 1 Глава 82",
            "Date": "16 января 2024",
            "Link": "/manga/i-have-90-billion-licking-gold/chapter/1-82",
            "Pages": {
                "ImageURL": ""
            }
        },
        {
            "Title": "Том 1 Глава 81",
            "Date": "9 января 2024",
            "Link": "/manga/i-have-90-billion-licking-gold/chapter/1-81",
            "Pages": {
                "ImageURL": ""
            }
        },
        {
            "Title": "Том 1 Глава 80",
            "Date": "9 января 2024",
            "Link": "/manga/i-have-90-billion-licking-gold/chapter/1-80",
            "Pages": {
                "ImageURL": ""
            }
        },
        {
            "Title": "Том 1 Глава 79",
            "Date": "9 января 2024",
            "Link": "/manga/i-have-90-billion-licking-gold/chapter/1-79",
            "Pages": {
                "ImageURL": ""
            }
        },
        {
            "Title": "Том 1 Глава 78",
            "Date": "9 января 2024",
            "Link": "/manga/i-have-90-billion-licking-gold/chapter/1-78",
            "Pages": {
                "ImageURL": ""
            }
        },
        {
            "Title": "Том 1 Глава 77",
            "Date": "9 января 2024",
            "Link": "/manga/i-have-90-billion-licking-gold/chapter/1-77",
            "Pages": {
                "ImageURL": ""
            }
        },
        {
            "Title": "Том 1 Глава 76",
            "Date": "9 января 2024",
            "Link": "/manga/i-have-90-billion-licking-gold/chapter/1-76",
            "Pages": {
                "ImageURL": ""
            }
        },
        {
            "Title": "Том 1 Глава 75",
            "Date": "9 января 2024",
            "Link": "/manga/i-have-90-billion-licking-gold/chapter/1-75",
            "Pages": {
                "ImageURL": ""
            }
        },
        {
            "Title": "Том 1 Глава 74",
            "Date": "31 декабря 2023",
            "Link": "/manga/i-have-90-billion-licking-gold/chapter/1-74",
            "Pages": {
                "ImageURL": ""
            }
        },
        {
            "Title": "Том 1 Глава 73",
            "Date": "30 декабря 2023",
            "Link": "/manga/i-have-90-billion-licking-gold/chapter/1-73",
            "Pages": {
                "ImageURL": ""
            }
        },
        {
            "Title": "Том 1 Глава 72",
            "Date": "28 декабря 2023",
            "Link": "/manga/i-have-90-billion-licking-gold/chapter/1-72",
            "Pages": {
                "ImageURL": ""
            }
        },
        {
            "Title": "Том 1 Глава 71",
            "Date": "27 декабря 2023",
            "Link": "/manga/i-have-90-billion-licking-gold/chapter/1-71",
            "Pages": {
                "ImageURL": ""
            }
        },
        {
            "Title": "Том 1 Глава 70",
            "Date": "26 декабря 2023",
            "Link": "/manga/i-have-90-billion-licking-gold/chapter/1-70",
            "Pages": {
                "ImageURL": ""
            }
        },
        {
            "Title": "Том 1 Глава 69",
            "Date": "25 декабря 2023",
            "Link": "/manga/i-have-90-billion-licking-gold/chapter/1-69",
            "Pages": {
                "ImageURL": ""
            }
        },
        {
            "Title": "Том 1 Глава 68",
            "Date": "23 декабря 2023",
            "Link": "/manga/i-have-90-billion-licking-gold/chapter/1-68",
            "Pages": {
                "ImageURL": ""
            }
        },
        {
            "Title": "Том 1 Глава 67",
            "Date": "22 декабря 2023",
            "Link": "/manga/i-have-90-billion-licking-gold/chapter/1-67",
            "Pages": {
                "ImageURL": ""
            }
        },
        {
            "Title": "Том 1 Глава 66",
            "Date": "21 декабря 2023",
            "Link": "/manga/i-have-90-billion-licking-gold/chapter/1-66",
            "Pages": {
                "ImageURL": ""
            }
        },
        {
            "Title": "Том 1 Глава 65",
            "Date": "19 декабря 2023",
            "Link": "/manga/i-have-90-billion-licking-gold/chapter/1-65",
            "Pages": {
                "ImageURL": ""
            }
        },
        {
            "Title": "Том 1 Глава 64",
            "Date": "18 декабря 2023",
            "Link": "/manga/i-have-90-billion-licking-gold/chapter/1-64",
            "Pages": {
                "ImageURL": ""
            }
        },
        {
            "Title": "Том 1 Глава 63",
            "Date": "17 декабря 2023",
            "Link": "/manga/i-have-90-billion-licking-gold/chapter/1-63",
            "Pages": {
                "ImageURL": ""
            }
        },
        {
            "Title": "Том 1 Глава 62",
            "Date": "17 декабря 2023",
            "Link": "/manga/i-have-90-billion-licking-gold/chapter/1-62",
            "Pages": {
                "ImageURL": ""
            }
        },
        {
            "Title": "Том 1 Глава 61",
            "Date": "15 декабря 2023",
            "Link": "/manga/i-have-90-billion-licking-gold/chapter/1-61",
            "Pages": {
                "ImageURL": ""
            }
        },
        {
            "Title": "Том 1 Глава 60",
            "Date": "14 декабря 2023",
            "Link": "/manga/i-have-90-billion-licking-gold/chapter/1-60",
            "Pages": {
                "ImageURL": ""
            }
        },
        {
            "Title": "Том 1 Глава 59",
            "Date": "13 декабря 2023",
            "Link": "/manga/i-have-90-billion-licking-gold/chapter/1-59",
            "Pages": {
                "ImageURL": ""
            }
        },
        {
            "Title": "Том 1 Глава 58",
            "Date": "12 декабря 2023",
            "Link": "/manga/i-have-90-billion-licking-gold/chapter/1-58",
            "Pages": {
                "ImageURL": ""
            }
        },
        {
            "Title": "Том 1 Глава 57",
            "Date": "12 декабря 2023",
            "Link": "/manga/i-have-90-billion-licking-gold/chapter/1-57",
            "Pages": {
                "ImageURL": ""
            }
        },
        {
            "Title": "Том 1 Глава 56",
            "Date": "9 декабря 2023",
            "Link": "/manga/i-have-90-billion-licking-gold/chapter/1-56",
            "Pages": {
                "ImageURL": ""
            }
        },
        {
            "Title": "Том 1 Глава 55",
            "Date": "9 декабря 2023",
            "Link": "/manga/i-have-90-billion-licking-gold/chapter/1-55",
            "Pages": {
                "ImageURL": ""
            }
        },
        {
            "Title": "Том 1 Глава 54",
            "Date": "9 декабря 2023",
            "Link": "/manga/i-have-90-billion-licking-gold/chapter/1-54",
            "Pages": {
                "ImageURL": ""
            }
        },
        {
            "Title": "Том 1 Глава 53",
            "Date": "7 декабря 2023",
            "Link": "/manga/i-have-90-billion-licking-gold/chapter/1-53",
            "Pages": {
                "ImageURL": ""
            }
        },
        {
            "Title": "Том 1 Глава 52",
            "Date": "7 декабря 2023",
            "Link": "/manga/i-have-90-billion-licking-gold/chapter/1-52",
            "Pages": {
                "ImageURL": ""
            }
        },
        {
            "Title": "Том 1 Глава 51",
            "Date": "3 декабря 2023",
            "Link": "/manga/i-have-90-billion-licking-gold/chapter/1-51",
            "Pages": {
                "ImageURL": ""
            }
        },
        {
            "Title": "Том 1 Глава 50",
            "Date": "2 декабря 2023",
            "Link": "/manga/i-have-90-billion-licking-gold/chapter/1-50",
            "Pages": {
                "ImageURL": ""
            }
        },
        {
            "Title": "Том 1 Глава 49",
            "Date": "2 декабря 2023",
            "Link": "/manga/i-have-90-billion-licking-gold/chapter/1-49",
            "Pages": {
                "ImageURL": ""
            }
        },
        {
            "Title": "Том 1 Глава 48",
            "Date": "29 ноября 2023",
            "Link": "/manga/i-have-90-billion-licking-gold/chapter/1-48",
            "Pages": {
                "ImageURL": ""
            }
        },
        {
            "Title": "Том 1 Глава 47",
            "Date": "27 ноября 2023",
            "Link": "/manga/i-have-90-billion-licking-gold/chapter/1-47",
            "Pages": {
                "ImageURL": ""
            }
        },
        {
            "Title": "Том 1 Глава 46",
            "Date": "27 ноября 2023",
            "Link": "/manga/i-have-90-billion-licking-gold/chapter/1-46",
            "Pages": {
                "ImageURL": ""
            }
        },
        {
            "Title": "Том 1 Глава 45",
            "Date": "24 ноября 2023",
            "Link": "/manga/i-have-90-billion-licking-gold/chapter/1-45",
            "Pages": {
                "ImageURL": ""
            }
        },
        {
            "Title": "Том 1 Глава 44",
            "Date": "24 ноября 2023",
            "Link": "/manga/i-have-90-billion-licking-gold/chapter/1-44",
            "Pages": {
                "ImageURL": ""
            }
        },
        {
            "Title": "Том 1 Глава 43",
            "Date": "22 ноября 2023",
            "Link": "/manga/i-have-90-billion-licking-gold/chapter/1-43",
            "Pages": {
                "ImageURL": ""
            }
        },
        {
            "Title": "Том 1 Глава 42",
            "Date": "22 ноября 2023",
            "Link": "/manga/i-have-90-billion-licking-gold/chapter/1-42",
            "Pages": {
                "ImageURL": ""
            }
        },
        {
            "Title": "Том 1 Глава 41",
            "Date": "21 ноября 2023",
            "Link": "/manga/i-have-90-billion-licking-gold/chapter/1-41",
            "Pages": {
                "ImageURL": ""
            }
        },
        {
            "Title": "Том 1 Глава 40",
            "Date": "21 ноября 2023",
            "Link": "/manga/i-have-90-billion-licking-gold/chapter/1-40",
            "Pages": {
                "ImageURL": ""
            }
        },
        {
            "Title": "Том 1 Глава 39",
            "Date": "18 ноября 2023",
            "Link": "/manga/i-have-90-billion-licking-gold/chapter/1-39",
            "Pages": {
                "ImageURL": ""
            }
        },
        {
            "Title": "Том 1 Глава 38",
            "Date": "17 ноября 2023",
            "Link": "/manga/i-have-90-billion-licking-gold/chapter/1-38",
            "Pages": {
                "ImageURL": ""
            }
        },
        {
            "Title": "Том 1 Глава 37",
            "Date": "17 ноября 2023",
            "Link": "/manga/i-have-90-billion-licking-gold/chapter/1-37",
            "Pages": {
                "ImageURL": ""
            }
        },
        {
            "Title": "Том 1 Глава 36",
            "Date": "14 ноября 2023",
            "Link": "/manga/i-have-90-billion-licking-gold/chapter/1-36",
            "Pages": {
                "ImageURL": ""
            }
        },
        {
            "Title": "Том 1 Глава 35",
            "Date": "12 ноября 2023",
            "Link": "/manga/i-have-90-billion-licking-gold/chapter/1-35",
            "Pages": {
                "ImageURL": ""
            }
        },
        {
            "Title": "Том 1 Глава 34",
            "Date": "12 ноября 2023",
            "Link": "/manga/i-have-90-billion-licking-gold/chapter/1-34",
            "Pages": {
                "ImageURL": ""
            }
        },
        {
            "Title": "Том 1 Глава 33",
            "Date": "10 ноября 2023",
            "Link": "/manga/i-have-90-billion-licking-gold/chapter/1-33",
            "Pages": {
                "ImageURL": ""
            }
        },
        {
            "Title": "Том 1 Глава 32",
            "Date": "10 ноября 2023",
            "Link": "/manga/i-have-90-billion-licking-gold/chapter/1-32",
            "Pages": {
                "ImageURL": ""
            }
        },
        {
            "Title": "Том 1 Глава 31",
            "Date": "10 ноября 2023",
            "Link": "/manga/i-have-90-billion-licking-gold/chapter/1-31",
            "Pages": {
                "ImageURL": ""
            }
        },
        {
            "Title": "Том 1 Глава 30",
            "Date": "6 ноября 2023",
            "Link": "/manga/i-have-90-billion-licking-gold/chapter/1-30",
            "Pages": {
                "ImageURL": ""
            }
        },
        {
            "Title": "Том 1 Глава 29",
            "Date": "6 ноября 2023",
            "Link": "/manga/i-have-90-billion-licking-gold/chapter/1-29",
            "Pages": {
                "ImageURL": ""
            }
        },
        {
            "Title": "Том 1 Глава 28",
            "Date": "6 ноября 2023",
            "Link": "/manga/i-have-90-billion-licking-gold/chapter/1-28",
            "Pages": {
                "ImageURL": ""
            }
        },
        {
            "Title": "Том 1 Глава 27",
            "Date": "6 ноября 2023",
            "Link": "/manga/i-have-90-billion-licking-gold/chapter/1-27",
            "Pages": {
                "ImageURL": ""
            }
        },
        {
            "Title": "Том 1 Глава 26",
            "Date": "6 ноября 2023",
            "Link": "/manga/i-have-90-billion-licking-gold/chapter/1-26",
            "Pages": {
                "ImageURL": ""
            }
        },
        {
            "Title": "Том 1 Глава 25",
            "Date": "6 ноября 2023",
            "Link": "/manga/i-have-90-billion-licking-gold/chapter/1-25",
            "Pages": {
                "ImageURL": ""
            }
        },
        {
            "Title": "Том 1 Глава 24",
            "Date": "6 ноября 2023",
            "Link": "/manga/i-have-90-billion-licking-gold/chapter/1-24",
            "Pages": {
                "ImageURL": ""
            }
        },
        {
            "Title": "Том 1 Глава 23",
            "Date": "6 ноября 2023",
            "Link": "/manga/i-have-90-billion-licking-gold/chapter/1-23",
            "Pages": {
                "ImageURL": ""
            }
        },
        {
            "Title": "Том 1 Глава 22",
            "Date": "6 ноября 2023",
            "Link": "/manga/i-have-90-billion-licking-gold/chapter/1-22",
            "Pages": {
                "ImageURL": ""
            }
        },
        {
            "Title": "Том 1 Глава 21",
            "Date": "6 ноября 2023",
            "Link": "/manga/i-have-90-billion-licking-gold/chapter/1-21",
            "Pages": {
                "ImageURL": ""
            }
        },
        {
            "Title": "Том 1 Глава 20",
            "Date": "6 ноября 2023",
            "Link": "/manga/i-have-90-billion-licking-gold/chapter/1-20",
            "Pages": {
                "ImageURL": ""
            }
        },
        {
            "Title": "Том 1 Глава 19",
            "Date": "6 ноября 2023",
            "Link": "/manga/i-have-90-billion-licking-gold/chapter/1-19",
            "Pages": {
                "ImageURL": ""
            }
        },
        {
            "Title": "Том 1 Глава 18",
            "Date": "6 ноября 2023",
            "Link": "/manga/i-have-90-billion-licking-gold/chapter/1-18",
            "Pages": {
                "ImageURL": ""
            }
        },
        {
            "Title": "Том 1 Глава 17",
            "Date": "6 ноября 2023",
            "Link": "/manga/i-have-90-billion-licking-gold/chapter/1-17",
            "Pages": {
                "ImageURL": ""
            }
        },
        {
            "Title": "Том 1 Глава 16",
            "Date": "6 ноября 2023",
            "Link": "/manga/i-have-90-billion-licking-gold/chapter/1-16",
            "Pages": {
                "ImageURL": ""
            }
        },
        {
            "Title": "Том 1 Глава 15",
            "Date": "6 ноября 2023",
            "Link": "/manga/i-have-90-billion-licking-gold/chapter/1-15",
            "Pages": {
                "ImageURL": ""
            }
        },
        {
            "Title": "Том 1 Глава 14",
            "Date": "6 ноября 2023",
            "Link": "/manga/i-have-90-billion-licking-gold/chapter/1-14",
            "Pages": {
                "ImageURL": ""
            }
        },
        {
            "Title": "Том 1 Глава 13",
            "Date": "6 ноября 2023",
            "Link": "/manga/i-have-90-billion-licking-gold/chapter/1-13",
            "Pages": {
                "ImageURL": ""
            }
        },
        {
            "Title": "Том 1 Глава 12",
            "Date": "6 ноября 2023",
            "Link": "/manga/i-have-90-billion-licking-gold/chapter/1-12",
            "Pages": {
                "ImageURL": ""
            }
        },
        {
            "Title": "Том 1 Глава 11",
            "Date": "6 ноября 2023",
            "Link": "/manga/i-have-90-billion-licking-gold/chapter/1-11",
            "Pages": {
                "ImageURL": ""
            }
        },
        {
            "Title": "Том 1 Глава 10",
            "Date": "6 ноября 2023",
            "Link": "/manga/i-have-90-billion-licking-gold/chapter/1-10",
            "Pages": {
                "ImageURL": ""
            }
        },
        {
            "Title": "Том 1 Глава 9",
            "Date": "6 ноября 2023",
            "Link": "/manga/i-have-90-billion-licking-gold/chapter/1-9",
            "Pages": {
                "ImageURL": ""
            }
        },
        {
            "Title": "Том 1 Глава 8",
            "Date": "6 ноября 2023",
            "Link": "/manga/i-have-90-billion-licking-gold/chapter/1-8",
            "Pages": {
                "ImageURL": ""
            }
        },
        {
            "Title": "Том 1 Глава 7",
            "Date": "6 ноября 2023",
            "Link": "/manga/i-have-90-billion-licking-gold/chapter/1-7",
            "Pages": {
                "ImageURL": ""
            }
        },
        {
            "Title": "Том 1 Глава 6",
            "Date": "6 ноября 2023",
            "Link": "/manga/i-have-90-billion-licking-gold/chapter/1-6",
            "Pages": {
                "ImageURL": ""
            }
        },
        {
            "Title": "Том 1 Глава 5",
            "Date": "6 ноября 2023",
            "Link": "/manga/i-have-90-billion-licking-gold/chapter/1-5",
            "Pages": {
                "ImageURL": ""
            }
        },
        {
            "Title": "Том 1 Глава 4",
            "Date": "6 ноября 2023",
            "Link": "/manga/i-have-90-billion-licking-gold/chapter/1-4",
            "Pages": {
                "ImageURL": ""
            }
        },
        {
            "Title": "Том 1 Глава 3",
            "Date": "6 ноября 2023",
            "Link": "/manga/i-have-90-billion-licking-gold/chapter/1-3",
            "Pages": {
                "ImageURL": ""
            }
        },
        {
            "Title": "Том 1 Глава 2",
            "Date": "6 ноября 2023",
            "Link": "/manga/i-have-90-billion-licking-gold/chapter/1-2",
            "Pages": {
                "ImageURL": ""
            }
        },
        {
            "Title": "Том 1 Глава 1",
            "Date": "6 ноября 2023",
            "Link": "/manga/i-have-90-billion-licking-gold/chapter/1-1",
            "Pages": {
                "ImageURL": ""
            }
        }
    ],
    "NumberOfChapters": "250",
    "Status": "Выпускается",
    "Year": "2023"
}